spinrewriterapi/__init__.py
spinrewriterapi/spinrewriterapi.py
spin_rewriter_api-1.0.0.dist-info/METADATA
spin_rewriter_api-1.0.0.dist-info/WHEEL
spin_rewriter_api-1.0.0.dist-info/top_level.txt
spin_rewriter_api-1.0.0.dist-info/RECORD
