Metadata-Version: 2.1
Name: spin-rewriter-api
Version: 1.0.0
Summary: Spin Rewriter is a revolutionary article spinner that uses ENL Semantic Spinning to understand the meaning of text. It produces high quality, unique and readable spun articles with a click.
Home-page: https://www.spinrewriter.com
Author: Spin Rewriter
Author-email: info@spinrewriter.com
License: Apache-2.0
Keywords: spinner spinrewriter seo article enl semantic language english writing text
Platform: UNKNOWN
Classifier: Development Status :: 5 - Production/Stable
Classifier: Topic :: Software Development :: Libraries :: Python Modules
Classifier: Natural Language :: English
Classifier: License :: OSI Approved :: Apache Software License
Classifier: Programming Language :: Python :: 3
Requires-Python: >=3.5
Requires-Dist: requests
